llm_gguf.py
llm_gguf-0.2.dist-info/LICENSE
llm_gguf-0.2.dist-info/METADATA
llm_gguf-0.2.dist-info/WHEEL
llm_gguf-0.2.dist-info/entry_points.txt
llm_gguf-0.2.dist-info/top_level.txt
llm_gguf-0.2.dist-info/RECORD
