Metadata-Version: 2.1
Name: llm-gguf
Version: 0.2
Summary: Run models distributed as GGUF files
Author: Simon Willison
License: Apache-2.0
Project-URL: Homepage, https://github.com/simonw/llm-gguf
Project-URL: Changelog, https://github.com/simonw/llm-gguf/releases
Project-URL: Issues, https://github.com/simonw/llm-gguf/issues
Project-URL: CI, https://github.com/simonw/llm-gguf/actions
Classifier: License :: OSI Approved :: Apache Software License
License-File: LICENSE
Requires-Dist: httpx
Requires-Dist: llm
Requires-Dist: llama-cpp-python
Provides-Extra: test
Requires-Dist: pytest; extra == "test"
